trie_pkg/__init__.py
trie_pkg/trie.py
trie_pkg-0.4.0.dist-info/METADATA
trie_pkg-0.4.0.dist-info/WHEEL
trie_pkg-0.4.0.dist-info/top_level.txt
trie_pkg-0.4.0.dist-info/RECORD
